cytotools/__init__.py
cytotools/dimension_reduction.py
cytotools/fda_norm.py
cytotools/feedback.py
cytotools/geometry.py
cytotools/kde.py
cytotools/neighbours.py
cytotools/read.py
cytotools/sampling.py
cytotools/tests/__init__.py
cytotools/tests/test_dimension_reduction.py
cytotools/tests/test_fda_norm.py
cytotools/tests/test_geometry.py
cytotools/tests/test_neighbours.py
cytotools/tests/test_read.py
cytotools/tests/test_sampling.py
cytotools/tests/test_transform.py
cytotools/transform.py
cytotools-0.1.22.dist-info/LICENSE
cytotools-0.1.22.dist-info/WHEEL
cytotools-0.1.22.dist-info/METADATA
cytotools-0.1.22.dist-info/RECORD
